odoo/addons/purchase_manual_currency/README.rst
odoo/addons/purchase_manual_currency/__init__.py
odoo/addons/purchase_manual_currency/__manifest__.py
odoo/addons/purchase_manual_currency/data/purchase_data.xml
odoo/addons/purchase_manual_currency/i18n/purchase_manual_currency.pot
odoo/addons/purchase_manual_currency/models/__init__.py
odoo/addons/purchase_manual_currency/models/purchase.py
odoo/addons/purchase_manual_currency/readme/CONTRIBUTORS.rst
odoo/addons/purchase_manual_currency/readme/DESCRIPTION.rst
odoo/addons/purchase_manual_currency/readme/USAGE.rst
odoo/addons/purchase_manual_currency/static/description/icon.png
odoo/addons/purchase_manual_currency/static/description/index.html
odoo/addons/purchase_manual_currency/tests/__init__.py
odoo/addons/purchase_manual_currency/tests/test_purchase_manual_currency.py
odoo/addons/purchase_manual_currency/views/purchase_views.xml
odoo13_addon_purchase_manual_currency-13.0.1.0.2.dist-info/METADATA
odoo13_addon_purchase_manual_currency-13.0.1.0.2.dist-info/WHEEL
odoo13_addon_purchase_manual_currency-13.0.1.0.2.dist-info/top_level.txt
odoo13_addon_purchase_manual_currency-13.0.1.0.2.dist-info/RECORD
